kafkareport/__init__.py
kafkareport/cli.py
kafkareport/helpers.py
kafkareport/logdirs.py
kafkareport-0.0.2.dist-info/LICENSE
kafkareport-0.0.2.dist-info/METADATA
kafkareport-0.0.2.dist-info/WHEEL
kafkareport-0.0.2.dist-info/entry_points.txt
kafkareport-0.0.2.dist-info/RECORD
