Metadata-Version: 2.1
Name: kafkareport
Version: 0.0.2
Summary: Reporting tool for kafka topics with retentions, sizes, earliest and latest message timestamps
Home-page: https://github.com/newvoll/kafkareport
License: MIT
Author: olmouse
Author-email: olmouse@newvoll.net
Requires-Python: >=3.9,<4.0
Classifier: License :: OSI Approved :: MIT License
Classifier: Programming Language :: Python :: 3
Classifier: Programming Language :: Python :: 3.9
Classifier: Programming Language :: Python :: 3.10
Classifier: Programming Language :: Python :: 3.11
Classifier: Programming Language :: Python :: 3.12
Requires-Dist: confluent_kafka (>=2.4.0,<3.0.0)
Requires-Dist: kafka-python (>=2.0.2,<3.0.0)
Requires-Dist: prettytable (>=3.10.0,<4.0.0)
Project-URL: Documentation, https://kafkareport.readthedocs.io/en/latest/index.html
Project-URL: Issues, https://github.com/newvoll/kafkareport/issues
Project-URL: Repository, https://github.com/newvoll/kafkareport
